distributed_compute/__init__.py
distributed_compute/auth.py
distributed_compute/cli.py
distributed_compute/coordinator.py
distributed_compute/exceptions.py
distributed_compute/protocol.py
distributed_compute/task.py
distributed_compute/worker.py
distributed_compute_locally-0.1.5.dist-info/licenses/LICENSE
distributed_compute_locally-0.1.5.dist-info/METADATA
distributed_compute_locally-0.1.5.dist-info/WHEEL
distributed_compute_locally-0.1.5.dist-info/entry_points.txt
distributed_compute_locally-0.1.5.dist-info/top_level.txt
distributed_compute_locally-0.1.5.dist-info/RECORD
