Metadata-Version: 2.4
Name: distributed-compute-locally
Version: 0.1.5
Summary: A library for distributing computational workloads across multiple devices
Home-page: https://github.com/Nebu0528/distributor
Author: Nebu0528
Author-email: nebu0528distributor@gmail.com
License: MIT
Project-URL: Homepage, https://github.com/Nebu0528/distributor
Project-URL: Documentation, https://github.com/Nebu0528/distributor#readme
Project-URL: Repository, https://github.com/Nebu0528/distributor
Project-URL: Issues, https://github.com/Nebu0528/distributor/issues
Keywords: distributed,computing,parallel,cluster,workload
Classifier: Development Status :: 3 - Alpha
Classifier: Intended Audience :: Developers
Classifier: Topic :: Software Development :: Libraries :: Python Modules
Classifier: Topic :: System :: Distributed Computing
Classifier: License :: OSI Approved :: MIT License
Classifier: Programming Language :: Python :: 3
Classifier: Programming Language :: Python :: 3.7
Classifier: Programming Language :: Python :: 3.8
Classifier: Programming Language :: Python :: 3.9
Classifier: Programming Language :: Python :: 3.10
Classifier: Programming Language :: Python :: 3.11
Classifier: Programming Language :: Python :: 3.12
Requires-Python: >=3.7
License-File: LICENSE
Requires-Dist: cloudpickle>=2.0.0
Requires-Dist: psutil>=5.8.0
Requires-Dist: prompt_toolkit>=3.0.0
Requires-Dist: rich>=13.0.0
Provides-Extra: dev
Requires-Dist: pytest>=7.0.0; extra == "dev"
Requires-Dist: pytest-cov>=3.0.0; extra == "dev"
Requires-Dist: black>=22.0.0; extra == "dev"
Requires-Dist: flake8>=4.0.0; extra == "dev"
Dynamic: author-email
Dynamic: home-page
Dynamic: license-file
Dynamic: requires-python
